AUTHOR.txt
README.txt
bootstrap.py
buildout.cfg
setup.py
z3c/__init__.py
z3c.resourceinclude.egg-info/PKG-INFO
z3c.resourceinclude.egg-info/SOURCES.txt
z3c.resourceinclude.egg-info/dependency_links.txt
z3c.resourceinclude.egg-info/entry_points.txt
z3c.resourceinclude.egg-info/namespace_packages.txt
z3c.resourceinclude.egg-info/not-zip-safe
z3c.resourceinclude.egg-info/requires.txt
z3c.resourceinclude.egg-info/top_level.txt
z3c/resourceinclude/README.txt
z3c/resourceinclude/__init__.py
z3c/resourceinclude/collector.py
z3c/resourceinclude/configure.zcml
z3c/resourceinclude/interfaces.py
z3c/resourceinclude/manager.py
z3c/resourceinclude/meta.zcml
z3c/resourceinclude/provider.pt
z3c/resourceinclude/provider.py
z3c/resourceinclude/testing.py
z3c/resourceinclude/viewlets.py
z3c/resourceinclude/zcml.py
z3c/resourceinclude/zcml.txt
z3c/resourceinclude/tests/__init__.py
z3c/resourceinclude/tests/test_doctests.py