Metadata-Version: 1.0
Name: z3c.resourceinclude
Version: 0.3
Summary: Machinery to include web resources based on request layer.
Home-page: UNKNOWN
Author: Malthe Borch
Author-email: mborch@gmail.com
License: ZPL
Platform: UNKNOWN
Classifier: Framework :: Zope2
Classifier: License :: OSI Approved :: Zope Public License
Classifier: Framework :: Zope3
Classifier: Programming Language :: Python
Classifier: Operating System :: OS Independent
Classifier: Topic :: Internet :: WWW/HTTP
Classifier: Topic :: Software Development :: Libraries :: Python Modules
